realsense_recorder/__init__.py
realsense_recorder/__main__.py
realsense_recorder/cmd/__init__.py
realsense_recorder/cmd/local_capture_static_interactive.py
realsense_recorder/cmd/local_record_seq.py
realsense_recorder/cmd/remote_record_seq.py
realsense_recorder/common/__init__.py
realsense_recorder/common/config.py
realsense_recorder/common/interaction.py
realsense_recorder/common/record.py
realsense_recorder/common/utils.py
realsense_recorder/io/BagReader.py
realsense_recorder/io/DirectoryReader.py
realsense_recorder/io/Sequence.py
realsense_recorder/io/__init__.py
realsense_recorder/scripts/__init__.py
realsense_recorder/scripts/configure.py
realsense_recorder-1.4.dist-info/METADATA
realsense_recorder-1.4.dist-info/WHEEL
realsense_recorder-1.4.dist-info/top_level.txt
realsense_recorder-1.4.dist-info/RECORD
