Metadata-Version: 2.1
Name: realsense-recorder
Version: 1.4
Summary: Realsense remote recorder
Author: davidliyutong
Author-email: davidliyutong@sjtu.edu.cn
Requires-Python: >=3.6
Requires-Dist: numpy (>=1.20)
Requires-Dist: tqdm (>=4.60)
Requires-Dist: rich (>=11.2.0)
Requires-Dist: pyrealsense2 (>=2.50.0.3812)
Requires-Dist: setuptools (>=60.9.3)
Requires-Dist: opencv-python (>=4.5.5.62)
Requires-Dist: uvicorn (>=0.20.0)
Requires-Dist: fastapi (>=0.87.0)
Requires-Dist: pyyaml (>=6.0)
Requires-Dist: flask (>=2.0.2)
Requires-Dist: gevent (>=21.12.0)
